build/lib/build/lib/build/lib/build/lib/build/lib/build/lib/test/path.py
build/lib/build/lib/build/lib/build/lib/build/lib/build/lib/test/test/path.py
build/lib/build/lib/build/lib/build/lib/build/lib/build/lib/test/test/test.py
build/lib/build/lib/build/lib/build/lib/build/lib/build/lib/wpath/__init__.py
build/lib/build/lib/build/lib/build/lib/build/lib/build/lib/wpath/code.py
build/lib/build/lib/build/lib/build/lib/build/lib/build/lib/wpath/log.py
build/lib/build/lib/build/lib/build/lib/build/lib/build/lib/wpath/path.py
build/lib/build/lib/build/lib/build/lib/build/lib/build/lib/wpath/time.py
build/lib/build/lib/build/lib/build/lib/build/lib/build/lib/wpath/types.py
build/lib/build/lib/build/lib/build/lib/build/lib/build/lib/wpath/utl.py
build/lib/build/lib/build/lib/build/lib/build/lib/build/lib/wpath/wprint.py
build/lib/build/lib/build/lib/build/lib/build/lib/test/path.py
build/lib/build/lib/build/lib/build/lib/build/lib/test/test/path.py
build/lib/build/lib/build/lib/build/lib/build/lib/test/test/test.py
build/lib/build/lib/build/lib/build/lib/build/lib/wpath/__init__.py
build/lib/build/lib/build/lib/build/lib/build/lib/wpath/code.py
build/lib/build/lib/build/lib/build/lib/build/lib/wpath/log.py
build/lib/build/lib/build/lib/build/lib/build/lib/wpath/path.py
build/lib/build/lib/build/lib/build/lib/build/lib/wpath/time.py
build/lib/build/lib/build/lib/build/lib/build/lib/wpath/types.py
build/lib/build/lib/build/lib/build/lib/build/lib/wpath/utl.py
build/lib/build/lib/build/lib/build/lib/build/lib/wpath/wprint.py
build/lib/build/lib/build/lib/build/lib/test/path.py
build/lib/build/lib/build/lib/build/lib/test/test/path.py
build/lib/build/lib/build/lib/build/lib/test/test/test.py
build/lib/build/lib/build/lib/build/lib/wpath/__init__.py
build/lib/build/lib/build/lib/build/lib/wpath/code.py
build/lib/build/lib/build/lib/build/lib/wpath/log.py
build/lib/build/lib/build/lib/build/lib/wpath/path.py
build/lib/build/lib/build/lib/build/lib/wpath/time.py
wpath-0.1.1.dist-info/LICENSE
wpath-0.1.1.dist-info/METADATA
wpath-0.1.1.dist-info/WHEEL
wpath-0.1.1.dist-info/top_level.txt
wpath-0.1.1.dist-info/zip-safe
wpath-0.1.1.dist-info/RECORD
