Metadata-Version: 2.1
Name: wpath
Version: 0.1.1
Summary: package help find the project root folder.
Home-page: https://github.com/cofepy
Author: Aeneas
Author-email: kai.he@taraxa.io
License: MIT
Keywords: project root folder workspace
Platform: UNKNOWN
Classifier: License :: OSI Approved :: MIT License
Classifier: Programming Language :: Python
Classifier: Intended Audience :: Developers
Classifier: Operating System :: OS Independent
Requires-Python: >=3.7
